compfs/__init__.py
compfs/metrics.py
compfs/thresholding_functions.py
compfs/utils.py
compfs/datasets/__init__.py
compfs/datasets/chem_featuriser.py
compfs/datasets/datasets.py
compfs/datasets/network.py
compfs/models/__init__.py
compfs/models/base_model.py
compfs/models/compfs.py
compfs/models/ensemble_stg.py
compfs/models/lasso.py
compfs/models/random_forests.py
compfs-0.0.2.dist-info/LICENSE.txt
compfs-0.0.2.dist-info/METADATA
compfs-0.0.2.dist-info/WHEEL
compfs-0.0.2.dist-info/top_level.txt
compfs-0.0.2.dist-info/RECORD
