Metadata-Version: 2.1
Name: compfs
Version: 0.0.2
Summary: Composite Feature Selection using Deep Ensembles
Home-page: UNKNOWN
Author: Alexander Norcliffe
License: MIT
Platform: UNKNOWN
Classifier: License :: OSI Approved :: MIT License
Classifier: Operating System :: OS Independent
Classifier: Programming Language :: Python :: 3
Classifier: Topic :: Scientific/Engineering :: Artificial Intelligence
Requires-Dist: jupyter
Requires-Dist: matplotlib
Requires-Dist: notebook
Requires-Dist: numpy (>=1.21.6)
Requires-Dist: pandas (>=1.3.5)
Requires-Dist: rdkit
Requires-Dist: scikit-learn (>=1.0.2)
Requires-Dist: scipy (>=1.7.3)
Requires-Dist: torch (>=1.12.1)
Requires-Dist: torchvision (>=0.13.1)
Requires-Dist: importlib-metadata ; python_version < "3.8"
Provides-Extra: testing
Requires-Dist: bandit ; extra == 'testing'
Requires-Dist: flake8 ; extra == 'testing'
Requires-Dist: ipykernel ; extra == 'testing'
Requires-Dist: isort ; extra == 'testing'
Requires-Dist: matplotlib ; extra == 'testing'
Requires-Dist: nbconvert ; extra == 'testing'
Requires-Dist: nltk ; extra == 'testing'
Requires-Dist: notebook ; extra == 'testing'
Requires-Dist: pre-commit ; extra == 'testing'
Requires-Dist: py ; extra == 'testing'
Requires-Dist: pytest ; extra == 'testing'
Requires-Dist: pytest-benchmark ; extra == 'testing'
Requires-Dist: pytest-cov ; extra == 'testing'
Requires-Dist: pytest-xdist[psutil] ; extra == 'testing'
Requires-Dist: pytest-xprocess ; extra == 'testing'
Requires-Dist: scipy (>=1.7.3) ; extra == 'testing'
Requires-Dist: seaborn ; extra == 'testing'
